{
  "generatedAt": "2025-10-13T00:51:57.532Z",
  "gameRequested": 1,
  "gameCompleted": 1,
  "searchDepth": 2,
  "aborted": false,
  "games": [
    {
      "gameNumber": 1,
      "moves": [
        {
          "turn": 0,
          "player": "red",
          "move": {
            "row": 0,
            "col": 7
          },
          "heuristics": {
            "goalDistance": 14.399999999999999,
            "isolatedBonus": 10,
            "firstEdgeTouch": 680,
            "edgeGapReduction": 1058,
            "redBaseBonus": 142,
            "redGlobalMultiplier": 273.7391310435307
          },
          "featureContext": {
            "turn": 0,
            "player": "red",
            "playerPegCount": 1,
            "opponentPegCount": 0
          },
          "valueModel": {
            "probability": 0.17744928170344595,
            "adjustment": -193.5304309779324,
            "logit": -1.5337253131179278
          },
          "heuristicScore": 1984.6087000655984
        },
        {
          "turn": 1,
          "player": "black",
          "move": {
            "row": 19,
            "col": 0
          },
          "heuristics": {
            "goalDistance": 14.399999999999999,
            "noThreatReduction": -250,
            "firstEdgeTouch": 500,
            "edgeGapReduction": 529,
            "edgeDefenseMiss": -350,
            "bottomBias": 228,
            "belowMaxRowBonus": 2850,
            "blackBasePenalty": -360,
            "blackGlobalScale": -543.2659270519408
          },
          "featureContext": {
            "turn": 1,
            "player": "black",
            "playerPegCount": 1,
            "opponentPegCount": 1
          },
          "valueModel": {
            "probability": 0.2612400652957466,
            "adjustment": -143.25596082255203,
            "logit": -1.039533241642241
          },
          "heuristicScore": 2474.8781121255074
        },
        {
          "turn": 2,
          "player": "red",
          "move": {
            "row": 2,
            "col": 8
          },
          "heuristics": {
            "friendlyConnections": 12,
            "friendlyDistance": 21,
            "goalDistance": 12,
            "centerBias": 1.5,
            "noThreatReduction": -250,
            "spanGain": 842.4,
            "edgeGapReduction": 92,
            "edgeDefenseMiss": -350,
            "redBaseBonus": 142,
            "redGlobalMultiplier": 68.91707721332426
          },
          "featureContext": {
            "turn": 2,
            "player": "red",
            "playerPegCount": 2,
            "opponentPegCount": 1
          },
          "valueModel": {
            "probability": 0.3463862209721282,
            "adjustment": -92.1682674167231,
            "logit": -0.6349622269645309
          },
          "heuristicScore": 499.64880979660114
        },
        {
          "turn": 3,
          "player": "black",
          "move": {
            "row": 20,
            "col": 2
          },
          "heuristics": {
            "friendlyConnections": 12,
            "friendlyDistance": 21,
            "goalDistance": 12,
            "noThreatReduction": -250,
            "spanGain": 356.4,
            "edgeGapReduction": 46,
            "edgeDefenseMiss": -350,
            "bottomBias": 240,
            "belowMaxRowBonus": 2700,
            "blackBasePenalty": -360,
            "blackGlobalScale": -419.4827621801272
          },
          "featureContext": {
            "turn": 3,
            "player": "black",
            "playerPegCount": 2,
            "opponentPegCount": 2
          },
          "valueModel": {
            "probability": 0.338432983149325,
            "adjustment": -96.94021011040499,
            "logit": -0.6702851979375793
          },
          "heuristicScore": 1910.9770277094676
        },
        {
          "turn": 4,
          "player": "red",
          "move": {
            "row": 4,
            "col": 9
          },
          "heuristics": {
            "friendlyConnections": 12,
            "friendlyDistance": 21,
            "goalDistance": 9.6,
            "centerBias": 3,
            "noThreatReduction": -250,
            "spanGain": 842.4,
            "edgeGapReduction": 92,
            "edgeDefenseMiss": -350,
            "redBaseBonus": 142,
            "redGlobalMultiplier": 63.74745078341122
          },
          "featureContext": {
            "turn": 4,
            "player": "red",
            "playerPegCount": 3,
            "opponentPegCount": 2
          },
          "valueModel": {
            "probability": 0.29403594566053387,
            "adjustment": -123.57843260367967,
            "logit": -0.8758622976472139
          },
          "heuristicScore": 462.16901817973155
        },
        {
          "turn": 5,
          "player": "black",
          "move": {
            "row": 19,
            "col": 4
          },
          "heuristics": {
            "friendlyConnections": 12,
            "friendlyDistance": 21,
            "goalDistance": 9.6,
            "centerBias": 0.5,
            "noThreatReduction": -250,
            "spanGain": 356.4,
            "edgeGapReduction": 46,
            "edgeDefenseMiss": -350,
            "bottomBias": 228,
            "belowMaxRowBonus": 2250,
            "blackBasePenalty": -360,
            "blackGlobalScale": -331.3755746570372
          },
          "featureContext": {
            "turn": 5,
            "player": "black",
            "playerPegCount": 3,
            "opponentPegCount": 3
          },
          "valueModel": {
            "probability": 0.29579235793552877,
            "adjustment": -122.52458523868273,
            "logit": -0.8674155440829501
          },
          "heuristicScore": 1509.5998401042798
        },
        {
          "turn": 6,
          "player": "red",
          "move": {
            "row": 6,
            "col": 10
          },
          "heuristics": {
            "friendlyConnections": 12,
            "friendlyDistance": 21,
            "goalDistance": 7.199999999999999,
            "centerBias": 4.5,
            "noThreatReduction": -250,
            "spanGain": 842.4,
            "edgeGapReduction": 92,
            "edgeDefenseMiss": -350,
            "redBaseBonus": 142,
            "redGlobalMultiplier": 59.050783171763804
          },
          "featureContext": {
            "turn": 6,
            "player": "red",
            "playerPegCount": 4,
            "opponentPegCount": 3
          },
          "valueModel": {
            "probability": 0.24661232470587346,
            "adjustment": -152.03260517647593,
            "logit": -1.1167623683298973
          },
          "heuristicScore": 428.11817799528774
        },
        {
          "turn": 7,
          "player": "black",
          "move": {
            "row": 20,
            "col": 6
          },
          "heuristics": {
            "friendlyConnections": 12,
            "friendlyDistance": 21,
            "goalDistance": 7.199999999999999,
            "centerBias": 1,
            "noThreatReduction": -600,
            "spanGain": 356.4,
            "edgeGapReduction": 46,
            "edgeDefenseMiss": -525,
            "noSpanReductionPenalty": -400,
            "bottomBias": 240,
            "belowMaxRowBonus": 2100,
            "blackBasePenalty": -360,
            "blackGlobalScale": -149.35490252171002
          },
          "featureContext": {
            "turn": 7,
            "player": "black",
            "playerPegCount": 4,
            "opponentPegCount": 4
          },
          "valueModel": {
            "probability": 0.38524909742324076,
            "adjustment": -68.85054154605554,
            "logit": -0.4673270179329578
          },
          "heuristicScore": 680.3945559322342
        },
        {
          "turn": 8,
          "player": "red",
          "move": {
            "row": 18,
            "col": 7
          },
          "heuristics": {
            "edgeDefenseBlock": 900,
            "opponentConnections": 35,
            "opponentDistance": 84,
            "goalDistance": 8.4,
            "centerBias": 2.5,
            "chainProximity": 270,
            "frontierProximity": 350,
            "frontierCapture": 550,
            "trailingPenalty": -36,
            "noThreatReduction": -600,
            "noSpanReductionPenalty": -400,
            "redBaseBonus": 142,
            "redGlobalMultiplier": 173.83500921571434
          },
          "featureContext": {
            "turn": 8,
            "player": "red",
            "playerPegCount": 5,
            "opponentPegCount": 4
          },
          "valueModel": {
            "probability": 0.13428134599702504,
            "adjustment": -219.43119240178498,
            "logit": -1.8636227800030978
          },
          "heuristicScore": 1260.3038168139294
        },
        {
          "turn": 9,
          "player": "black",
          "move": {
            "row": 19,
            "col": 8
          },
          "heuristics": {
            "friendlyConnections": 12,
            "friendlyDistance": 21,
            "opponentDistance": 96,
            "goalDistance": 4.8,
            "centerBias": 2.5,
            "noThreatReduction": -600,
            "spanGain": 356.4,
            "edgeGapReduction": 46,
            "edgeDefenseMiss": -525,
            "noSpanReductionPenalty": -400,
            "bottomBias": 228,
            "belowMaxRowBonus": 150,
            "blackBasePenalty": -360,
            "blackGlobalScale": 193.46014637740313
          },
          "featureContext": {
            "turn": 9,
            "player": "black",
            "playerPegCount": 5,
            "opponentPegCount": 5
          },
          "valueModel": {
            "probability": 0.322535681690712,
            "adjustment": -106.4785909855728,
            "logit": -0.7421431136477521
          },
          "heuristicScore": -881.3184446081696
        },
        {
          "turn": 10,
          "player": "red",
          "move": {
            "row": 17,
            "col": 9
          },
          "heuristics": {
            "edgeDefenseBlock": 900,
            "friendlyConnections": 12,
            "opponentConnections": 35,
            "friendlyDistance": 21,
            "opponentDistance": 84,
            "goalDistance": 7.199999999999999,
            "centerBias": 4,
            "chainProximity": 270,
            "frontierProximity": 350,
            "frontierCapture": 550,
            "trailingPenalty": -36,
            "noThreatReduction": -600,
            "noSpanReductionPenalty": -400,
            "redBaseBonus": 142,
            "redGlobalMultiplier": 178.40130339567213
          },
          "featureContext": {
            "turn": 10,
            "player": "red",
            "playerPegCount": 6,
            "opponentPegCount": 5
          },
          "valueModel": {
            "probability": 0.12634691037158588,
            "adjustment": -224.1918537770485,
            "logit": -1.9336519936393317
          },
          "heuristicScore": 1293.4094496186235
        },
        {
          "turn": 11,
          "player": "black",
          "move": {
            "row": 20,
            "col": 10
          },
          "heuristics": {
            "friendlyConnections": 12,
            "friendlyDistance": 21,
            "opponentDistance": 72,
            "goalDistance": 2.4,
            "centerBias": 3,
            "noThreatReduction": -600,
            "spanGain": 356.4,
            "edgeGapReduction": 46,
            "edgeDefenseMiss": -525,
            "noSpanReductionPenalty": -400,
            "bottomBias": 240,
            "belowMaxRowBonus": 300,
            "blackBasePenalty": -360,
            "blackGlobalScale": 173.02366432398702
          },
          "featureContext": {
            "turn": 11,
            "player": "black",
            "playerPegCount": 6,
            "opponentPegCount": 6
          },
          "valueModel": {
            "probability": 0.28492903403715764,
            "adjustment": -129.04257957770542,
            "logit": -0.9201416449798616
          },
          "heuristicScore": -788.2189152537185
        },
        {
          "turn": 12,
          "player": "red",
          "move": {
            "row": 18,
            "col": 11
          },
          "heuristics": {
            "edgeDefenseBlock": 900,
            "friendlyConnections": 12,
            "friendlyDistance": 21,
            "opponentDistance": 60,
            "goalDistance": 6,
            "centerBias": 5.5,
            "chainProximity": 210,
            "frontierProximity": 280,
            "trailingPenalty": -24,
            "noThreatReduction": -600,
            "noSpanReductionPenalty": -400,
            "redBaseBonus": 142,
            "redGlobalMultiplier": 62.99705395331916
          },
          "featureContext": {
            "turn": 12,
            "player": "red",
            "playerPegCount": 7,
            "opponentPegCount": 6
          },
          "valueModel": {
            "probability": 0.1353859786804082,
            "adjustment": -218.76841279175508,
            "logit": -1.8541533889008752
          },
          "heuristicScore": 456.7286411615641
        },
        {
          "turn": 13,
          "player": "black",
          "move": {
            "row": 21,
            "col": 12
          },
          "heuristics": {
            "friendlyConnections": 12,
            "friendlyDistance": 21,
            "opponentDistance": 72,
            "goalDistance": 1.2,
            "centerBias": 3,
            "noThreatReduction": -600,
            "spanGain": 356.4,
            "edgeGapReduction": 46,
            "edgeDefenseMiss": -525,
            "noSpanReductionPenalty": -400,
            "bottomBias": 252,
            "belowMaxRowBonus": 450,
            "blackBasePenalty": -360,
            "blackGlobalScale": 144.71038579982957
          },
          "featureContext": {
            "turn": 13,
            "player": "black",
            "playerPegCount": 7,
            "opponentPegCount": 7
          },
          "valueModel": {
            "probability": 0.27908902037194905,
            "adjustment": -132.54658777683056,
            "logit": -0.9489848613768502
          },
          "heuristicScore": -659.2362019770012
        },
        {
          "turn": 14,
          "player": "red",
          "move": {
            "row": 19,
            "col": 13
          },
          "heuristics": {
            "edgeDefenseBlock": 900,
            "friendlyConnections": 12,
            "opponentConnections": 35,
            "friendlyDistance": 21,
            "opponentDistance": 84,
            "goalDistance": 9.6,
            "centerBias": 3.5,
            "chainProximity": 270,
            "frontierProximity": 350,
            "frontierCapture": 550,
            "trailingPenalty": -36,
            "noThreatReduction": -600,
            "noSpanReductionPenalty": -400,
            "redBaseBonus": 142,
            "redGlobalMultiplier": 180.28615709418028
          },
          "featureContext": {
            "turn": 14,
            "player": "red",
            "playerPegCount": 8,
            "opponentPegCount": 7
          },
          "valueModel": {
            "probability": 0.1428141363977123,
            "adjustment": -214.31151816137262,
            "logit": -1.7921107327112622
          },
          "heuristicScore": 1307.0746389328076
        },
        {
          "turn": 15,
          "player": "black",
          "move": {
            "row": 20,
            "col": 14
          },
          "heuristics": {
            "friendlyConnections": 12,
            "friendlyDistance": 21,
            "opponentDistance": 96,
            "goalDistance": 3.5999999999999996,
            "centerBias": 2.5,
            "noThreatReduction": -600,
            "spanGain": 356.4,
            "edgeGapReduction": 46,
            "edgeDefenseMiss": -525,
            "noSpanReductionPenalty": -400,
            "bottomBias": 240,
            "belowMaxRowBonus": 150,
            "blackBasePenalty": -360,
            "blackGlobalScale": 192.6412798062733
          },
          "featureContext": {
            "turn": 15,
            "player": "black",
            "playerPegCount": 8,
            "opponentPegCount": 8
          },
          "valueModel": {
            "probability": 0.3121177795715442,
            "adjustment": -112.7293322570735,
            "logit": -0.7902370168391948
          },
          "heuristicScore": -877.5880524508002
        },
        {
          "turn": 16,
          "player": "red",
          "move": {
            "row": 20,
            "col": 15
          },
          "heuristics": {
            "edgeDefenseBlock": 900,
            "friendlyConnections": 12,
            "friendlyDistance": 21,
            "opponentDistance": 108,
            "goalDistance": 10.799999999999999,
            "centerBias": 2,
            "chainProximity": 330,
            "frontierProximity": 280,
            "trailingPenalty": -24,
            "noThreatReduction": -600,
            "noSpanReductionPenalty": -400,
            "redBaseBonus": 142,
            "redGlobalMultiplier": 97.50659081612129
          },
          "featureContext": {
            "turn": 16,
            "player": "red",
            "playerPegCount": 9,
            "opponentPegCount": 8
          },
          "valueModel": {
            "probability": 0.21269365433459728,
            "adjustment": -172.38380739924162,
            "logit": -1.3087645423074872
          },
          "heuristicScore": 706.9227834168796
        },
        {
          "turn": 17,
          "player": "black",
          "move": {
            "row": 21,
            "col": 16
          },
          "heuristics": {
            "edgeDefenseBlock": 900,
            "friendlyConnections": 12,
            "friendlyDistance": 21,
            "opponentDistance": 96,
            "goalDistance": 6,
            "centerBias": 1,
            "chainProximity": 300,
            "frontierProximity": 315,
            "connectorProximity": 385,
            "noThreatReduction": -600,
            "spanGain": 356.4,
            "edgeGapReduction": 46,
            "noSpanReductionPenalty": -400,
            "bottomBias": 252,
            "belowMaxRowBonus": 150,
            "blackBasePenalty": -360,
            "blackGlobalScale": -236.90265781438703
          },
          "featureContext": {
            "turn": 17,
            "player": "black",
            "playerPegCount": 9,
            "opponentPegCount": 9
          },
          "valueModel": {
            "probability": 0.22620979457765714,
            "adjustment": -164.27412325340575,
            "logit": -1.2298379211577393
          },
          "heuristicScore": 1079.2232189322071
        },
        {
          "turn": 18,
          "player": "red",
          "move": {
            "row": 21,
            "col": 17
          },
          "heuristics": {
            "edgeConnectorTarget": 500,
            "edgeDefenseBlock": 900,
            "friendlyConnections": 12,
            "friendlyDistance": 21,
            "opponentDistance": 108,
            "goalDistance": 12,
            "centerBias": 0.5,
            "chainProximity": 330,
            "frontierProximity": 280,
            "connectorProximity": 330,
            "trailingPenalty": -24,
            "noThreatReduction": -600,
            "edgeGapReduction": 46,
            "noSpanReductionPenalty": -400,
            "redBaseBonus": 142,
            "redGlobalMultiplier": 237.47498425976028
          },
          "featureContext": {
            "turn": 18,
            "player": "red",
            "playerPegCount": 10,
            "opponentPegCount": 9
          },
          "valueModel": {
            "probability": 0.21119775270583743,
            "adjustment": -173.28134837649756,
            "logit": -1.317720741109989
          },
          "heuristicScore": 1721.6936358832627
        },
        {
          "turn": 19,
          "player": "black",
          "move": {
            "row": 22,
            "col": 18
          },
          "heuristics": {
            "edgeDefenseBlock": 900,
            "friendlyConnections": 12,
            "friendlyDistance": 21,
            "opponentDistance": 96,
            "goalDistance": 8.4,
            "chainProximity": 300,
            "frontierProximity": 315,
            "connectorProximity": 385,
            "noThreatReduction": -600,
            "spanGain": 356.4,
            "edgeGapReduction": 46,
            "noSpanReductionPenalty": -400,
            "bottomBias": 264,
            "belowMaxRowBonus": 150,
            "blackBasePenalty": -360,
            "blackGlobalScale": -243.07194340462527
          },
          "featureContext": {
            "turn": 19,
            "player": "black",
            "playerPegCount": 10,
            "opponentPegCount": 10
          },
          "valueModel": {
            "probability": 0.26099947596875156,
            "adjustment": -143.40031441874908,
            "logit": -1.0407802305184242
          },
          "heuristicScore": 1107.3277421766259
        },
        {
          "turn": 20,
          "player": "red",
          "move": {
            "row": 22,
            "col": 19
          },
          "heuristics": {
            "edgeConnectorTarget": 500,
            "edgeDefenseBlock": 900,
            "friendlyConnections": 12,
            "friendlyDistance": 21,
            "opponentDistance": 108,
            "goalDistance": 13.2,
            "chainProximity": 330,
            "frontierProximity": 280,
            "connectorProximity": 330,
            "trailingPenalty": -12,
            "noThreatReduction": -600,
            "edgeGapReduction": 46,
            "noSpanReductionPenalty": -400,
            "redBaseBonus": 142,
            "redGlobalMultiplier": 241.90162223588968
          },
          "featureContext": {
            "turn": 20,
            "player": "red",
            "playerPegCount": 11,
            "opponentPegCount": 10
          },
          "valueModel": {
            "probability": 0.23614189829051904,
            "adjustment": -158.3148610256886,
            "logit": -1.1739491528879304
          },
          "heuristicScore": 1753.786761210201
        },
        {
          "turn": 21,
          "player": "black",
          "move": {
            "row": 22,
            "col": 14
          },
          "heuristics": {
            "friendlyConnections": 24,
            "opponentConnections": 35,
            "friendlyDistance": 24,
            "opponentDistance": 84,
            "goalDistance": 3.5999999999999996,
            "centerBias": 1.5,
            "chainProximity": 270,
            "frontierProximity": 350,
            "frontierCapture": 550,
            "connectorProximity": 440,
            "connectorCapture": 700,
            "trailingPenalty": -6,
            "noThreatReduction": -600,
            "edgeDefenseMiss": -525,
            "noSpanReductionPenalty": -400,
            "bottomBias": 264,
            "blackBasePenalty": -360,
            "blackGlobalScale": -103.65691807167279
          },
          "featureContext": {
            "turn": 21,
            "player": "black",
            "playerPegCount": 11,
            "opponentPegCount": 11
          },
          "valueModel": {
            "probability": 0.03461961177474789,
            "adjustment": -279.22823293515125,
            "logit": -3.3281018725737903
          },
          "heuristicScore": 472.21484899317585
        },
        {
          "turn": 22,
          "player": "red",
          "move": {
            "row": 23,
            "col": 17
          },
          "heuristics": {
            "edgeConnectorTarget": 500,
            "friendlyConnections": 12,
            "opponentConnections": 35,
            "friendlyDistance": 24,
            "opponentDistance": 96,
            "goalDistance": 14.399999999999999,
            "chainProximity": 300,
            "frontierProximity": 245,
            "connectorProximity": 220,
            "trailingPenalty": -18,
            "noThreatReduction": -600,
            "firstEdgeTouch": 680,
            "edgeGapReduction": 46,
            "edgeFinishAdvance": 3520,
            "noSpanReductionPenalty": -400,
            "redBaseBonus": 142,
            "redGlobalMultiplier": 749.2789082948859
          },
          "featureContext": {
            "turn": 22,
            "player": "red",
            "playerPegCount": 12,
            "opponentPegCount": 11
          },
          "valueModel": {
            "probability": 0.27765529473839956,
            "adjustment": -133.40682315696026,
            "logit": -0.9561220587329563
          },
          "heuristicScore": 5432.272085137925
        },
        {
          "turn": 23,
          "player": "black",
          "move": {
            "row": 20,
            "col": 20
          },
          "heuristics": {
            "opponentConnections": 35,
            "friendlyDistance": 18,
            "opponentDistance": 84,
            "goalDistance": 10.799999999999999,
            "chainProximity": 270,
            "frontierProximity": 350,
            "frontierCapture": 550,
            "connectorProximity": 440,
            "connectorCapture": 700,
            "trailingPenalty": -18,
            "noThreatReduction": -600,
            "edgeDefenseMiss": -525,
            "noSpanReductionPenalty": -400,
            "blackBasePenalty": -360,
            "blackGlobalScale": -50.40348360577334
          },
          "featureContext": {
            "turn": 23,
            "player": "black",
            "playerPegCount": 12,
            "opponentPegCount": 12
          },
          "valueModel": {
            "probability": 0.04203225560901205,
            "adjustment": -274.7806466345928,
            "logit": -3.1263767934458304
          },
          "heuristicScore": 229.61586975963402
        },
        {
          "turn": 24,
          "player": "red",
          "move": {
            "row": 8,
            "col": 9
          },
          "heuristics": {
            "friendlyConnections": 12,
            "friendlyDistance": 21,
            "opponentDistance": 72,
            "goalDistance": 4.8,
            "centerBias": 4.5,
            "chainProximity": 240,
            "frontierProximity": 245,
            "trailingPenalty": -18,
            "noThreatReduction": -600,
            "spanGain": 842.4,
            "edgeGapReduction": 92,
            "edgeFinishAdvance": 3820,
            "noSpanReductionPenalty": -400,
            "redBaseBonus": 142,
            "redGlobalMultiplier": 696.0839403687671
          },
          "featureContext": {
            "turn": 24,
            "player": "red",
            "playerPegCount": 13,
            "opponentPegCount": 12
          },
          "valueModel": {
            "probability": 0.28804104550799575,
            "adjustment": -127.17537269520255,
            "logit": -0.9049172724588224
          },
          "heuristicScore": 5046.608567673564
        },
        {
          "turn": 25,
          "player": "black",
          "move": {
            "row": 21,
            "col": 18
          },
          "heuristics": {
            "friendlyConnections": 12,
            "opponentConnections": 35,
            "friendlyDistance": 27,
            "opponentDistance": 108,
            "goalDistance": 8.4,
            "chainProximity": 330,
            "frontierProximity": 350,
            "frontierCapture": 550,
            "connectorProximity": 440,
            "connectorCapture": 700,
            "trailingPenalty": -24,
            "noThreatReduction": -600,
            "edgeDefenseMiss": -525,
            "noSpanReductionPenalty": -400,
            "blackBasePenalty": -360,
            "blackGlobalScale": -67.82100004883041
          },
          "featureContext": {
            "turn": 25,
            "player": "black",
            "playerPegCount": 13,
            "opponentPegCount": 13
          },
          "valueModel": {
            "probability": 0.04230555600768874,
            "adjustment": -274.61666639538674,
            "logit": -3.1196103499771555
          },
          "heuristicScore": 308.9623335557829
        },
        {
          "turn": 26,
          "player": "red",
          "move": {
            "row": 15,
            "col": 8
          },
          "heuristics": {
            "friendlyConnections": 12,
            "friendlyDistance": 21,
            "opponentDistance": 72,
            "goalDistance": 4.8,
            "centerBias": 4.5,
            "chainProximity": 240,
            "frontierProximity": 245,
            "trailingPenalty": -18,
            "noThreatReduction": -600,
            "edgeGapReduction": 92,
            "edgeFinishAdvance": 3820,
            "noSpanReductionPenalty": -400,
            "redBaseBonus": 142,
            "redGlobalMultiplier": 547.8591392093027
          },
          "featureContext": {
            "turn": 26,
            "player": "red",
            "playerPegCount": 14,
            "opponentPegCount": 13
          },
          "valueModel": {
            "probability": 0.14803270009690647,
            "adjustment": -211.1803799418561,
            "logit": -1.7501149497376105
          },
          "heuristicScore": 3971.9787592674465
        },
        {
          "turn": 27,
          "player": "black",
          "move": {
            "row": 21,
            "col": 21
          },
          "heuristics": {
            "opponentConnections": 35,
            "friendlyDistance": 24,
            "opponentDistance": 84,
            "goalDistance": 12,
            "chainProximity": 270,
            "frontierProximity": 350,
            "frontierCapture": 550,
            "connectorProximity": 440,
            "connectorCapture": 700,
            "trailingPenalty": -6,
            "noThreatReduction": -600,
            "edgeDefenseMiss": -525,
            "noSpanReductionPenalty": -400,
            "blackBasePenalty": -360,
            "blackGlobalScale": -54.30856463903327
          },
          "featureContext": {
            "turn": 27,
            "player": "black",
            "playerPegCount": 14,
            "opponentPegCount": 14
          },
          "valueModel": {
            "probability": 0.046190413324381965,
            "adjustment": -272.28575200537085,
            "logit": -3.0276917840924273
          },
          "heuristicScore": 247.40568335559593
        },
        {
          "turn": 28,
          "player": "red",
          "move": {
            "row": 13,
            "col": 7
          },
          "heuristics": {
            "friendlyConnections": 12,
            "friendlyDistance": 21,
            "opponentDistance": 36,
            "goalDistance": 2.4,
            "centerBias": 5,
            "chainProximity": 150,
            "frontierProximity": 210,
            "trailingPenalty": -12,
            "noThreatReduction": -600,
            "spanGain": 842.4,
            "edgeGapReduction": 92,
            "edgeFinishAdvance": 4120,
            "noSpanReductionPenalty": -400,
            "redBaseBonus": 142,
            "redGlobalMultiplier": 716.9626260671266
          },
          "featureContext": {
            "turn": 28,
            "player": "red",
            "playerPegCount": 15,
            "opponentPegCount": 14
          },
          "valueModel": {
            "probability": 0.2670273548659056,
            "adjustment": -139.78358708045664,
            "logit": -1.0097572763035745
          },
          "heuristicScore": 5197.97903898667
        },
        {
          "turn": 29,
          "player": "black",
          "move": {
            "row": 12,
            "col": 5
          },
          "heuristics": {
            "edgeDefenseBlock": 900,
            "opponentConnections": 35,
            "friendlyDistance": 6,
            "opponentDistance": 84,
            "goalDistance": 8.4,
            "centerBias": 4.5,
            "chainProximity": 270,
            "frontierProximity": 350,
            "frontierCapture": 550,
            "trailingPenalty": -36,
            "noThreatReduction": -600,
            "noSpanReductionPenalty": -400,
            "blackBasePenalty": -360,
            "blackGlobalScale": -104.37536194316723
          },
          "featureContext": {
            "turn": 29,
            "player": "black",
            "playerPegCount": 15,
            "opponentPegCount": 15
          },
          "valueModel": {
            "probability": 0.1132718698441406,
            "adjustment": -232.03687809351564,
            "logit": -2.0577475735036734
          },
          "heuristicScore": 475.4877599633172
        },
        {
          "turn": 30,
          "player": "red",
          "move": {
            "row": 11,
            "col": 6
          },
          "heuristics": {
            "friendlyConnections": 12,
            "friendlyDistance": 21,
            "opponentDistance": 96,
            "goalDistance": 1.2,
            "centerBias": 5,
            "chainProximity": 90,
            "frontierProximity": 105,
            "noThreatReduction": -600,
            "spanGain": 842.4,
            "edgeGapReduction": 92,
            "edgeFinishAdvance": 4420,
            "noSpanReductionPenalty": -400,
            "redBaseBonus": 142,
            "redGlobalMultiplier": 754.8894867637903
          },
          "featureContext": {
            "turn": 30,
            "player": "red",
            "playerPegCount": 16,
            "opponentPegCount": 15
          },
          "valueModel": {
            "probability": 0.3190988204561515,
            "adjustment": -108.5407077263091,
            "logit": -0.7579163480114215
          },
          "heuristicScore": 5472.9487790374815
        },
        {
          "turn": 31,
          "player": "black",
          "move": {
            "row": 10,
            "col": 6
          },
          "heuristics": {
            "edgeDefenseBlock": 900,
            "friendlyConnections": 12,
            "friendlyDistance": 21,
            "opponentDistance": 108,
            "goalDistance": 7.199999999999999,
            "centerBias": 4.5,
            "chainProximity": 330,
            "frontierProximity": 280,
            "trailingPenalty": -24,
            "noThreatReduction": -600,
            "noSpanReductionPenalty": -400,
            "blackBasePenalty": -360,
            "blackGlobalScale": -12.919543782043247
          },
          "featureContext": {
            "turn": 31,
            "player": "black",
            "playerPegCount": 16,
            "opponentPegCount": 16
          },
          "valueModel": {
            "probability": 0.1551254053892892,
            "adjustment": -206.92475676642647,
            "logit": -1.6949543507701657
          },
          "heuristicScore": 58.85569945153033
        },
        {
          "turn": 32,
          "player": "red",
          "move": {
            "row": 10,
            "col": 8
          },
          "heuristics": {
            "friendlyConnections": 12,
            "friendlyDistance": 21,
            "opponentDistance": 96,
            "goalDistance": 1.2,
            "centerBias": 5,
            "chainProximity": 90,
            "frontierProximity": 105,
            "noThreatReduction": -600,
            "spanGain": 842.4,
            "edgeGapReduction": 92,
            "edgeFinishAdvance": 4420,
            "noSpanReductionPenalty": -400,
            "redBaseBonus": 142,
            "redGlobalMultiplier": 754.8894867637903
          },
          "featureContext": {
            "turn": 30,
            "player": "red",
            "playerPegCount": 16,
            "opponentPegCount": 15
          },
          "valueModel": {
            "probability": 0.3190988204561515,
            "adjustment": -108.5407077263091,
            "logit": -0.7579163480114215
          },
          "heuristicScore": 5472.9487790374815
        }
      ],
      "summary": {
        "boardSize": 24,
        "totalMoves": 33,
        "winner": "red",
        "gameOver": true,
        "draw": false
      },
      "stalled": false
    }
  ]
}